markdownipy/__init__.py
markdownipy/markdownipy.py
Markdownipy-1.0.0.dist-info/LICENSE
Markdownipy-1.0.0.dist-info/METADATA
Markdownipy-1.0.0.dist-info/WHEEL
Markdownipy-1.0.0.dist-info/top_level.txt
Markdownipy-1.0.0.dist-info/RECORD
