Metadata-Version: 2.1
Name: Markdownipy
Version: 1.0.0
Summary: Markdownipy, python markdown generator library
Home-page: https://github.com/fbgencer/markdownipy
Author: fbgencer
Author-email: fbgencer8@gmail.com
License: MIT
Platform: UNKNOWN
Requires-Python: >=3.6
License-File: LICENSE
